dvible-1.0.6.data/purelib/dvible/Makefile
dvible-1.0.6.data/purelib/dvible/__init__.py
dvible-1.0.6.data/purelib/dvible/blescan.py
dvible-1.0.6.data/purelib/dvible/bluez-src.tgz
dvible-1.0.6.data/purelib/dvible/btle.py
dvible-1.0.6.data/purelib/dvible/dvible-helper
dvible-1.0.6.data/purelib/dvible/dvible-helper.c
dvible-1.0.6.data/purelib/dvible/get_services.py
dvible-1.0.6.data/purelib/dvible/scanner.py
dvible-1.0.6.data/purelib/dvible/sensortag.py
dvible-1.0.6.data/purelib/dvible/thingy52.py
dvible-1.0.6.data/purelib/dvible/uuids.json
dvible-1.0.6.dist-info/METADATA
dvible-1.0.6.dist-info/RECORD
dvible-1.0.6.dist-info/WHEEL
dvible-1.0.6.dist-info/entry_points.txt
dvible-1.0.6.dist-info/top_level.txt
