Metadata-Version: 2.1
Name: dvible
Version: 1.0.6
Summary: Python module for interfacing with BLE devices through Bluez
Home-page: https://daviorze.com.br
Author: Davi Orzechowski
Author-email: daviorze@gmail.com
License: UNKNOWN
Keywords: Bluetooth,Bluetooth Smart,BLE,Bluetooth Low Energy
Platform: UNKNOWN
Classifier: Programming Language :: Python :: 2.7
Classifier: Programming Language :: Python :: 3.3
Classifier: Programming Language :: Python :: 3.4
